ipyxturtle/__init__.py
ipyxturtle/_version.py
ipyxturtle/ipyxturtle.py
ipyxturtle/labextension/build_log.json
ipyxturtle/labextension/package.json
ipyxturtle/labextension/static/23d3dc43a7ebe54f7dcbf2bc658de693.png
ipyxturtle/labextension/static/97466b07c2424184308f22f5928448ec.png
ipyxturtle/labextension/static/lib_index_js.dbbd5168bec0a9c0196a.js
ipyxturtle/labextension/static/lib_labplugin_js.e43fcb9a847342284cb9.js
ipyxturtle/labextension/static/remoteEntry.ae6982fb2881ee8a9a6f.js
ipyxturtle/labextension/static/style.js
ipyxturtle/labextension/static/vendors-node_modules_xturtle_index_js.2f164945a16dfa74cd72.js
ipyxturtle/nbextension/23d3dc43a7ebe54f7dcbf2bc658de693.png
ipyxturtle/nbextension/97466b07c2424184308f22f5928448ec.png
ipyxturtle/nbextension/extension.js
ipyxturtle/nbextension/index.js
ipyxturtle-0.1.0a0.data/data/etc/jupyter/nbconfig/notebook.d/ipyxturtle.json
ipyxturtle-0.1.0a0.data/data/share/jupyter/labextensions/ipyxturtle/build_log.json
ipyxturtle-0.1.0a0.data/data/share/jupyter/labextensions/ipyxturtle/install.json
ipyxturtle-0.1.0a0.data/data/share/jupyter/labextensions/ipyxturtle/package.json
ipyxturtle-0.1.0a0.data/data/share/jupyter/labextensions/ipyxturtle/static/23d3dc43a7ebe54f7dcbf2bc658de693.png
ipyxturtle-0.1.0a0.data/data/share/jupyter/labextensions/ipyxturtle/static/97466b07c2424184308f22f5928448ec.png
ipyxturtle-0.1.0a0.data/data/share/jupyter/labextensions/ipyxturtle/static/lib_index_js.dbbd5168bec0a9c0196a.js
ipyxturtle-0.1.0a0.data/data/share/jupyter/labextensions/ipyxturtle/static/lib_index_js.dbbd5168bec0a9c0196a.js.map
ipyxturtle-0.1.0a0.data/data/share/jupyter/labextensions/ipyxturtle/static/lib_labplugin_js.e43fcb9a847342284cb9.js
ipyxturtle-0.1.0a0.data/data/share/jupyter/labextensions/ipyxturtle/static/lib_labplugin_js.e43fcb9a847342284cb9.js.map
ipyxturtle-0.1.0a0.data/data/share/jupyter/labextensions/ipyxturtle/static/remoteEntry.ae6982fb2881ee8a9a6f.js
ipyxturtle-0.1.0a0.dist-info/LICENSE
ipyxturtle-0.1.0a0.dist-info/METADATA
ipyxturtle-0.1.0a0.dist-info/WHEEL
ipyxturtle-0.1.0a0.dist-info/top_level.txt
ipyxturtle-0.1.0a0.dist-info/RECORD
